setup.py
Ella_Series.egg-info/PKG-INFO
Ella_Series.egg-info/SOURCES.txt
Ella_Series.egg-info/dependency_links.txt
Ella_Series.egg-info/requires.txt
Ella_Series.egg-info/top_level.txt
ella_series/__init__.py
ella_series/admin.py
ella_series/models.py
ella_series/newman_admin.py
ella_series/register.py